sphinx_vcs_changelog/__init__.py
sphinx_vcs_changelog/changelog.py
sphinx_vcs_changelog/changelog_by_file.py
sphinx_vcs_changelog/cmdline.py
sphinx_vcs_changelog/constants.py
sphinx_vcs_changelog/decorator.py
sphinx_vcs_changelog/exceptions.py
sphinx_vcs_changelog/factory.py
sphinx_vcs_changelog/repository.py
sphinx_vcs_changelog/filters/__init__.py
sphinx_vcs_changelog/filters/added_since.py
sphinx_vcs_changelog/filters/match_groups.py
sphinx_vcs_changelog/filters/matched_regexp.py
sphinx_vcs_changelog/filters/results_count.py
sphinx_vcs_changelog-0.1.1.dist-info/COPYING
sphinx_vcs_changelog-0.1.1.dist-info/LICENSE
sphinx_vcs_changelog-0.1.1.dist-info/METADATA
sphinx_vcs_changelog-0.1.1.dist-info/WHEEL
sphinx_vcs_changelog-0.1.1.dist-info/entry_points.txt
sphinx_vcs_changelog-0.1.1.dist-info/top_level.txt
sphinx_vcs_changelog-0.1.1.dist-info/RECORD
